flict/__init__.py
flict/__main__.py
flict/impl.py
flict/flictlib/__init__.py
flict/flictlib/arbiter.py
flict/flictlib/compatibility.py
flict/flictlib/flict_config.py
flict/flictlib/lic_comp.py
flict/flictlib/license.py
flict/flictlib/license_parser.py
flict/flictlib/logger.py
flict/flictlib/return_codes.py
flict/flictlib/utils.py
flict/flictlib/format/__init__.py
flict/flictlib/format/common.py
flict/flictlib/format/dot_format.py
flict/flictlib/format/factory.py
flict/flictlib/format/format.py
flict/flictlib/format/json_format.py
flict/flictlib/format/markdown_format.py
flict/flictlib/format/text_format.py
flict/flictlib/project/__init__.py
flict/flictlib/project/reader.py
flict/var/__init__.py
flict/var/alias.json
flict/var/scancode-licenses.json
flict-1.3.0.dist-info/LICENSE
flict-1.3.0.dist-info/METADATA
flict-1.3.0.dist-info/WHEEL
flict-1.3.0.dist-info/entry_points.txt
flict-1.3.0.dist-info/top_level.txt
flict-1.3.0.dist-info/RECORD
