Metadata-Version: 2.1
Name: flict
Version: 1.3.0
Summary: FOSS License Compatibility Tool
Home-page: https://github.com/vinland-technology/flict
Author: Henrik Sanklef
Author-email: hesa@sandklef.com
License: GPL-3.0-or-later
Platform: UNKNOWN
Classifier: Development Status :: 4 - Beta
Classifier: Environment :: Console
Classifier: Intended Audience :: Developers
Classifier: Intended Audience :: Legal Industry
Classifier: License :: OSI Approved :: GNU General Public License v3 or later (GPLv3+)
Classifier: Natural Language :: English
Classifier: Operating System :: POSIX :: Linux
Classifier: Programming Language :: Python :: 3 :: Only
Classifier: Programming Language :: Python :: 3.9
Classifier: Programming Language :: Python :: 3.10
Classifier: Programming Language :: Python :: 3.11
Classifier: Programming Language :: Python :: 3.12
Classifier: Programming Language :: Python :: 3.13
Classifier: Programming Language :: Python :: 3
Classifier: Topic :: Software Development :: Quality Assurance
Requires-Python: >=3.8
License-File: LICENSE
Requires-Dist: foss-flame~=0.20
Requires-Dist: license-expression~=30.4
Requires-Dist: osadl-matrix==2024.5.22.10535
Provides-Extra: dev
Requires-Dist: bump2version~=1.0; extra == "dev"
Requires-Dist: dataclasses~=0.6; extra == "dev"
Requires-Dist: dlint~=0.16; extra == "dev"
Requires-Dist: flake8-2020~=1.8; extra == "dev"
Requires-Dist: flake8-bandit~=4.1; extra == "dev"
Requires-Dist: flake8-broken-line~=1.0; extra == "dev"
Requires-Dist: flake8-bugbear~=24.8; extra == "dev"
Requires-Dist: flake8-builtins~=2.5; extra == "dev"
Requires-Dist: flake8-coding~=1.3; extra == "dev"
Requires-Dist: flake8-commas~=4.0; extra == "dev"
Requires-Dist: flake8-comprehensions~=3.16; extra == "dev"
Requires-Dist: flake8-debugger~=4.1; extra == "dev"
Requires-Dist: flake8-docstrings~=1.7; extra == "dev"
Requires-Dist: flake8-eradicate~=1.5; extra == "dev"
Requires-Dist: flake8-executable~=2.1; extra == "dev"
Requires-Dist: flake8-fixme~=1.1; extra == "dev"
Requires-Dist: flake8-functions==0.0.8; extra == "dev"
Requires-Dist: flake8-isort==6.1.1; extra == "dev"
Requires-Dist: flake8-mutable~=1.2; extra == "dev"
Requires-Dist: flake8-pep3101~=2.1; extra == "dev"
Requires-Dist: flake8-print~=5.0; extra == "dev"
Requires-Dist: flake8-quotes~=3.4; extra == "dev"
Requires-Dist: flake8-requirements~=2.2; extra == "dev"
Requires-Dist: flake8-string-format~=0.3; extra == "dev"
Requires-Dist: flake8-variables-names==0.0.6; extra == "dev"
Requires-Dist: flake8~=7.1; extra == "dev"
Requires-Dist: jsonschema~=4.23; extra == "dev"
Requires-Dist: pytest-bandit~=0.6; extra == "dev"
Requires-Dist: pytest-cov~=6.0; extra == "dev"
Requires-Dist: pytest-forked~=1.6; extra == "dev"
Requires-Dist: pytest-icdiff~=0.9; extra == "dev"
Requires-Dist: pytest-random-order~=1.1; extra == "dev"
Requires-Dist: pytest-socket~=0.7; extra == "dev"
Requires-Dist: pytest-sugar~=1.0; extra == "dev"
Requires-Dist: pytest-tldr~=0.2; extra == "dev"
Requires-Dist: pytest-xdist~=3.6; extra == "dev"
Requires-Dist: pytest~=8.3; extra == "dev"
Requires-Dist: reuse~=4.0; extra == "dev"
Requires-Dist: twine~=5.1; extra == "dev"
Requires-Dist: wheel~=0.44; extra == "dev"
